QtFrameless/__init__.py
QtFrameless/button.py
QtFrameless/home.png
QtFrameless/qt_api.py
QtFrameless/style.py
QtFrameless/titleBar.py
QtFrameless/window.py
QtFrameless-0.1.4.dist-info/LICENSE
QtFrameless-0.1.4.dist-info/METADATA
QtFrameless-0.1.4.dist-info/WHEEL
QtFrameless-0.1.4.dist-info/top_level.txt
QtFrameless-0.1.4.dist-info/RECORD
