Metadata-Version: 2.1
Name: QtFrameless
Version: 0.1.4
Summary: A resizable movable frameless window for PySide6.
Author-email: alexpdev <alexpdev@pm.me>
License: Apache License
Project-URL: homepage, https://github.com/alexpdev/QtFrameless
Project-URL: repository, https://github.com
Project-URL: documentation, https://alexpdev.github.io/QtFrameless
Project-URL: changelog, https://alexpdev.github.io/QtFrameless/changelog/
Project-URL: issues, https://github.com/alexpdev/QtFrameless/issues
Keywords: Qt,GUI,Graphical-User-Interface,Widget,Frameless
Classifier: Development Status :: 4 - Beta
Classifier: Operating System :: OS Independent
Classifier: Programming Language :: Python
Classifier: Programming Language :: Python :: 3
Classifier: Programming Language :: Python :: 3.8
Classifier: Programming Language :: Python :: 3.9
Classifier: Programming Language :: Python :: 3.10
Classifier: Programming Language :: Python :: 3 :: Only
Classifier: Intended Audience :: End Users/Desktop
Classifier: Intended Audience :: Developers
Classifier: License :: OSI Approved :: Apache Software License
Requires-Python: >=3.8
License-File: LICENSE
Requires-Dist: PySide6
